<formComponent>
  <id>LABEL</id>
  <type>LABEL</type>
  <componentDefaultHeight>20</componentDefaultHeight>
  <componentDefaultWidth>400</componentDefaultWidth>
  <jsAdminObject>sitools.admin.forms.noParam.label</jsAdminObject>
  <jsUserObject>sitools.common.forms.components.Label</jsUserObject>
  <fileUrlAdmin>/sitools/client-admin/js/forms/componentsAdminDef/NoParam/Label.js</fileUrlAdmin>
  <fileUrlUser>/sitools/common/js/forms/components/Label.js</fileUrlUser>
  <imageUrl>/sitools/common/res/images/formComponents/label.gif</imageUrl>
  <priority>1</priority>
</formComponent>